python_fsa/__init__.py
python_fsa/dfa.py
python_fsa/graph.py
python_fsa/nfa.py
python_fsa-0.0.5.dist-info/LICENSE
python_fsa-0.0.5.dist-info/METADATA
python_fsa-0.0.5.dist-info/WHEEL
python_fsa-0.0.5.dist-info/top_level.txt
python_fsa-0.0.5.dist-info/RECORD
