Metadata-Version: 2.1
Name: python-fsa
Version: 0.0.5
Summary: Finite State Automata utilities
License: CC0
Requires-Python: >=3.10
License-File: LICENSE
Provides-Extra: graphviz
Requires-Dist: pygraphviz ~=1.10 ; extra == 'graphviz'
